[
    {
        "areas": [],
        "enum": "A Lei Maria da Penha objetiva proteger a mulher da viol\u00eancia dom\u00e9stica e familiar que lhe cause morte, les\u00e3o, sofrimento f\u00edsico, sexual ou psicol\u00f3gico, e dano moral ou patrimonial, desde que o crime seja cometido no \u00e2mbito da unidade dom\u00e9stica, da fam\u00edlia ou em qualquer rela\u00e7\u00e3o \u00edntima de afeto.  Diante deste quadro, ap\u00f3s agredir sua antiga companheira, porque ela n\u00e3o quis retomar o relacionamento encerrado, causando-lhe les\u00f5es leves, Jorge o (a) procura para saber se sua conduta far\u00e1 incidir as regras da Lei n\u00ba 11.340/06.\n\n Considerando o que foi acima destacado, voc\u00ea, como advogado (a) ir\u00e1 esclarec\u00ea-lo de que",
        "filename": "2016-20.txt",
        "number": "63",
        "options": [
            {
                "correct": null,
                "letter": "A",
                "text": "o crime em tese praticado ostenta a natureza de infra\u00e7\u00e3o de menor potencial ofensivo."
            },
            {
                "correct": null,
                "letter": "B",
                "text": "a viol\u00eancia dom\u00e9stica de que trata a Lei Maria da Penha abrange qualquer rela\u00e7\u00e3o \u00edntima de afeto, sendo indispens\u00e1vel a coabita\u00e7\u00e3o."
            },
            {
                "correct": true,
                "letter": "C",
                "text": "a agress\u00e3o do companheiro contra a companheira, mesmo cessado o relacionamento, mas que ocorra em decorr\u00eancia dele, caracteriza a viol\u00eancia dom\u00e9stica e autoriza a incid\u00eancia da Lei n\u00ba 11.340/06."
            },
            {
                "correct": null,
                "letter": "D",
                "text": "ao contr\u00e1rio da transa\u00e7\u00e3o penal, em tese se mostra poss\u00edvel a suspens\u00e3o condicional do processo na hip\u00f3tese de delito sujeito ao rito da Lei Maria da Penha."
            }
        ],
        "valid": true
    }
]
