[
    {
        "areas": [
            "LABOUR-PROCEDURE"
        ],
        "enum": "Assinale a alternativa que apresente requisitos intr\u00ednsecos gen\u00e9ricos de admissibilidade recursal.",
        "filename": "2010-02.txt",
        "number": "52",
        "options": [
            {
                "correct": true,
                "letter": "A",
                "text": "Capacidade, legitimidade e interesse."
            },
            {
                "correct": null,
                "letter": "B",
                "text": "Preparo, interesse e representa\u00e7\u00e3o processual."
            },
            {
                "correct": null,
                "letter": "C",
                "text": "Representa\u00e7\u00e3o processual, preparo e tempestividade."
            },
            {
                "correct": null,
                "letter": "D",
                "text": "Legitimidade, tempestividade e preparo."
            }
        ],
        "valid": true
    }
]
