[{"areas": ["BUSINESS"], "enum": "A respeito do nome empresarial, \u00e9 correto afirmar que", "filename": "2012-06a.txt", "number": "50", "options": [{"correct": null, "letter": "A", "text": "o nome empresarial pode ser objeto de contrato de compra e venda."}, {"correct": null, "letter": "B", "text": "a sociedade em conta de participa\u00e7\u00e3o, por possuir personalidade jur\u00eddica, pode adotar firma ou denomina\u00e7\u00e3o."}, {"correct": true, "letter": "C", "text": "a sociedade an\u00f4nima ser\u00e1 designada somente por meio de denomina\u00e7\u00e3o."}, {"correct": null, "letter": "D", "text": "a sociedade limitada ser\u00e1 designada somente por meio de firma."}], "valid": true}]