[{"areas": ["ETHICS"], "enum": "T\u00edcio, advogado militante h\u00e1 longos anos, tem entrevero com o Juiz da Comarca W que, em altos brados, afirma que o caus\u00eddico \u00e9 praticante de chicanas e atos de m\u00e1-f\u00e9 processual, sendo conhecido como ex\u00edmio procrastinador da atividade processual, obstando o bom desenvolvimento da Justi\u00e7a. \u00c0 luz das normas do Regulamento Geral do Estatuto da Advocacia e da OAB, \u00e9 correto afirmar:", "filename": "2012-07.txt", "number": "10", "options": [{"correct": null, "letter": "A", "text": "Tais atos permitem o agravo do advogado se houver requerimento pessoal ao Presidente da Seccional."}, {"correct": null, "letter": "B", "text": "Havendo requerimento de qualquer pessoa poder\u00e1 ocorrer o desagravo ap\u00f3s decis\u00e3o do Relator do processo."}, {"correct": true, "letter": "C", "text": "O desagravo \u00e9 p\u00fablico e promovido pelo Conselho competente podendo ocorrer de of\u00edcio."}, {"correct": null, "letter": "D", "text": "Caso constatado que a ofensa \u00e9 decorrente do exerc\u00edcio da profiss\u00e3o poder\u00e1 ocorrer o arquivamento sum\u00e1rio."}], "valid": true}]