[{"enum": "Jos\u00e9 \u00e9 advogado de Jo\u00e3o em processo judicial que este promove contra Matheus. Encantado com as sucessivas campanhas de concilia\u00e7\u00e3o, busca obter o apoio do r\u00e9u para um acordo, sem consultar previamente o patrono da parte contr\u00e1ria, Valter.\n\n Nos termos do C\u00f3digo de \u00c9tica, deve o advogado", "number": "7", "valid": true, "options": [{"pmi": [0.0, 0.0, 0.0, 0.0], "correct": null, "letter": "A", "text": "buscar a concilia\u00e7\u00e3o a qualquer pre\u00e7o por ser um objetivo da moderna Jurisdi\u00e7\u00e3o."}, {"pmi": [0.0, 0.0, 0.0, 0.0], "correct": true, "letter": "B", "text": "abster-se de entender-se diretamente com a parte adversa que tenha patrono constitu\u00eddo, sem o assentimento deste."}, {"pmi": [-0.09256721605761341, 0.0, 0.0, 0.0], "correct": null, "letter": "C", "text": "entender-se com as partes na presen\u00e7a de autoridade sem necessidade de comunica\u00e7\u00e3o ao ex adverso."}, {"pmi": [-0.027394841513754153, 0.0, 0.0, 0.0], "correct": null, "letter": "D", "text": "participar de campanhas de concilia\u00e7\u00e3o e, caso infrut\u00edferas, tentar o acordo extrajudicial diretamente com a parte contr\u00e1ria."}], "filename": "2013-11.txt", "areas": ["ETHICS"]}]