[{"filename": "2010-01.txt", "enum": "Considere que, em processo trabalhista, as empresas Delta e Echo sejam condenadas, de forma solid\u00e1ria, pelo juiz do trabalho, que ambas interponham recurso ordin\u00e1rio, que apenas Delta efetue o dep\u00f3sito recursal, e nenhuma delas pleiteie a exclus\u00e3o da lide. Nessa situa\u00e7\u00e3o hipot\u00e9tica, o recurso apresentado pela empresa Echo", "areas": ["LABOUR-PROCEDURE"], "valid": true, "number": "80", "options": [{"pmi": [0.0, 0.0, 0.0, 0.0], "letter": "A", "text": "ser\u00e1 deserto, em raz\u00e3o de n\u00e3o ter sido efetuado o dep\u00f3sito recursal.", "correct": null}, {"pmi": [0.0, 0.0, 0.0, 0.0], "letter": "B", "text": "ser\u00e1 intempestivo, em raz\u00e3o de n\u00e3o ter sido efetuado o dep\u00f3sito recursal.", "correct": null}, {"pmi": [0.0, 0.0, 0.0, 0.0], "letter": "C", "text": "dever\u00e1 ser conhecido, mas improvido, em raz\u00e3o de n\u00e3o ter sido efetuado o dep\u00f3sito recursal.", "correct": null}, {"pmi": [-0.03432169623541218, 0.0, 0.0, 0.0], "letter": "D", "text": "estar\u00e1 apto a ser conhecido, visto que, sendo a condena\u00e7\u00e3o solid\u00e1ria, o dep\u00f3sito efetuado pela empresa Delta aproveita \u00e0 empresa Echo.", "correct": true}]}]