[
    {
        "filename": "2010-02.txt",
        "enum": "Com rela\u00e7\u00e3o ao Direito Coletivo do Trabalho, assinale a alternativa correta.",
        "areas": [
            "LABOUR"
        ],
        "number": "43",
        "valid": true,
        "options": [
            {
                "text": "Acordo coletivo do trabalho \u00e9 o acordo de car\u00e1ter normativo pelo qual dois ou mais sindicatos representativos de categorias econ\u00f4micas e profissionais estipulam condi\u00e7\u00f5es de trabalho aplic\u00e1veis, no \u00e2mbito das respectivas representa\u00e7\u00f5es, \u00e0s rela\u00e7\u00f5es individuais de trabalho.",
                "correct": null,
                "letter": "A",
                "pmi": [
                    -0.03369357197435975,
                    0.0,
                    0.0,
                    0.0
                ]
            },
            {
                "text": "Na greve em servi\u00e7os ou atividades essenciais, ficam as entidades sindicais ou os trabalhadores, conforme o caso, obrigados a comunicar a decis\u00e3o aos empregadores e aos usu\u00e1rios com anteced\u00eancia m\u00ednima de 72 (setenta e duas) horas da paralisa\u00e7\u00e3o.",
                "correct": true,
                "letter": "B",
                "pmi": [
                    -0.04905697792695685,
                    0.0,
                    0.0,
                    0.0
                ]
            },
            {
                "text": "As centrais sindicais, por for\u00e7a de lei, podem celebrar acordos e conven\u00e7\u00f5es coletivos de trabalho.",
                "correct": null,
                "letter": "C",
                "pmi": [
                    0.0,
                    0.0,
                    0.0,
                    0.0
                ]
            },
            {
                "text": "O recolhimento da contribui\u00e7\u00e3o sindical obrigat\u00f3ria (\u201cimposto sindical\u201d) somente \u00e9 exigido dos empregados sindicalizados, em face do princ\u00edpio da liberdade sindical.",
                "correct": null,
                "letter": "D",
                "pmi": [
                    0.0,
                    0.0,
                    0.0,
                    0.0
                ]
            }
        ]
    }
]
