[
    {
        "areas": [],
        "enum": "Pedro, em determinado momento, recebeu uma proposta de Ant\u00f4nio, colega de col\u00e9gio, que se prop\u00f4s a agenciar a indica\u00e7\u00e3o de novos clientes, mediante pagamento de comiss\u00e3o, a ser retirada dos honor\u00e1rios cobrados aos clientes, nos moldes da pr\u00e1tica desenvolvida entre vendedores da \u00e1rea comercial.\n\n Com base no caso relatado, observadas as regras do Estatuto da OAB, assinale a afirmativa correta.",
        "filename": "2015-16.txt",
        "number": "6",
        "options": [
            {
                "correct": null,
                "letter": "A",
                "pmi": [
                    0.0,
                    0.0,
                    0.0,
                    0.0
                ],
                "text": "O advogado pode aceitar a sugest\u00e3o, tendo em vista a moderna vis\u00e3o mercantil da profiss\u00e3o."
            },
            {
                "correct": null,
                "letter": "B",
                "pmi": [
                    0.0,
                    0.0,
                    0.0,
                    0.0
                ],
                "text": "Caso a Seccional da OAB autorize, registrando a aven\u00e7a escrita entre o advogado e o agenciador, \u00e9 poss\u00edvel."
            },
            {
                "correct": null,
                "letter": "C",
                "pmi": [
                    0.0,
                    0.0,
                    0.0,
                    0.0
                ],
                "text": "Sendo publicizada a rela\u00e7\u00e3o entre o advogado e o agenciador, est\u00e1 preenchido o requisito legal."
            },
            {
                "correct": true,
                "letter": "D",
                "pmi": [
                    0.0,
                    0.0,
                    0.0,
                    0.0
                ],
                "text": "H\u00e1 veda\u00e7\u00e3o quanto ao agenciamento de clientela, sem exce\u00e7\u00f5es."
            }
        ],
        "valid": true
    }
]
