[
    {
        "areas": [
            "LABOUR"
        ],
        "enum": "Com rela\u00e7\u00e3o \u00e0s normas de prote\u00e7\u00e3o ao trabalho da mulher, inseridas na CLT, assinale a op\u00e7\u00e3o correta.",
        "filename": "2010-01.txt",
        "number": "68",
        "options": [
            {
                "correct": null,
                "letter": "A",
                "text": "O trabalho noturno ter\u00e1 sal\u00e1rio superior ao diurno, com percentual de acr\u00e9scimo de, no m\u00ednimo, 25%.",
                "pmi": [
                    0.0,
                    0.0,
                    0.0,
                    0.0
                ]
            },
            {
                "correct": true,
                "letter": "B",
                "text": "Em caso de prorroga\u00e7\u00e3o do hor\u00e1rio normal de trabalho, \u00e9 obrigat\u00f3ria a concess\u00e3o de descanso de, no m\u00ednimo, quinze minutos antes do in\u00edcio do hor\u00e1rio extraordin\u00e1rio do trabalho.",
                "pmi": [
                    0.06319765501977646,
                    0.0,
                    0.0,
                    0.0
                ]
            },
            {
                "correct": null,
                "letter": "C",
                "text": "Na admiss\u00e3o ao emprego, \u00e9 facultado ao empregador exigir atestado ou exame para a comprova\u00e7\u00e3o de gravidez.",
                "pmi": [
                    0.0,
                    0.0,
                    0.0,
                    0.0
                ]
            },
            {
                "correct": null,
                "letter": "D",
                "text": "Entre duas jornadas de trabalho, deve haver um intervalo de, no m\u00ednimo, doze horas consecutivas destinadas ao repouso.",
                "pmi": [
                    0.0,
                    0.0,
                    0.0,
                    0.0
                ]
            }
        ],
        "valid": true
    }
]
